igi_file_transformation_contract/__init__.py
igi_file_transformation_contract/exceptions.py
igi_file_transformation_contract/interface.py
igi_file_transformation_contract/progress.py
igi_file_transformation_contract/result.py
igi_file_transformation_contract-0.0.7.dist-info/METADATA
igi_file_transformation_contract-0.0.7.dist-info/WHEEL
igi_file_transformation_contract-0.0.7.dist-info/top_level.txt
igi_file_transformation_contract-0.0.7.dist-info/RECORD
