Metadata-Version: 2.1
Name: igi-file-transformation-contract
Version: 0.0.7
Summary: Interface and helpers for file transformations.
Home-page: https://github.com/IGILtd/data_transformation_scripts/tree/master/import_file_formats/gc
Author: IGI
Author-email: chris.prosser@igiltd.com
License: MIT
Platform: UNKNOWN
Classifier: Development Status :: 4 - Beta
Classifier: Environment :: Web Environment
Classifier: Intended Audience :: Developers
Classifier: License :: OSI Approved :: MIT License
Classifier: Operating System :: OS Independent
Classifier: Programming Language :: Python
Classifier: Programming Language :: Python :: 3
Classifier: Programming Language :: Python :: 3.7
Classifier: Programming Language :: Python :: 3.8
Classifier: Programming Language :: Python :: 3.9
Classifier: Programming Language :: Python :: 3.10
Classifier: Topic :: Software Development :: Libraries :: Python Modules
Classifier: Topic :: Software Development :: Pre-processors
Classifier: Topic :: Text Processing
Classifier: Typing :: Typed
Requires-Python: >=3.7
